aiowechatpayv3/__init__.py
aiowechatpayv3/apply4subject.py
aiowechatpayv3/applyment.py
aiowechatpayv3/businesscircle.py
aiowechatpayv3/capital.py
aiowechatpayv3/complaint.py
aiowechatpayv3/core.py
aiowechatpayv3/fapiao.py
aiowechatpayv3/goldplan.py
aiowechatpayv3/marketing.py
aiowechatpayv3/media.py
aiowechatpayv3/merchantrisk.py
aiowechatpayv3/parking.py
aiowechatpayv3/payscore.py
aiowechatpayv3/profitsharing.py
aiowechatpayv3/smartguide.py
aiowechatpayv3/transaction.py
aiowechatpayv3/transfer.py
aiowechatpayv3/type.py
aiowechatpayv3/utils.py
aiowechatpayv3-0.1.0.dist-info/LICENSE
aiowechatpayv3-0.1.0.dist-info/METADATA
aiowechatpayv3-0.1.0.dist-info/WHEEL
aiowechatpayv3-0.1.0.dist-info/RECORD
