Metadata-Version: 2.1
Name: aiowechatpayv3
Version: 0.1.0
Summary: 
Author: yuxf
Author-email: yuxf@unitechs.com
Requires-Python: >=3.8,<4.0
Classifier: Programming Language :: Python :: 3
Classifier: Programming Language :: Python :: 3.8
Classifier: Programming Language :: Python :: 3.9
Classifier: Programming Language :: Python :: 3.10
Classifier: Programming Language :: Python :: 3.11
Requires-Dist: cryptography (>=40.0.1,<41.0.0)
Requires-Dist: httpx (>=0.23.3,<0.24.0)
